yaml2json.py
searchie_tools_yaml2json-0.1.16.dist-info/DESCRIPTION.rst
searchie_tools_yaml2json-0.1.16.dist-info/METADATA
searchie_tools_yaml2json-0.1.16.dist-info/RECORD
searchie_tools_yaml2json-0.1.16.dist-info/WHEEL
searchie_tools_yaml2json-0.1.16.dist-info/entry_points.txt
searchie_tools_yaml2json-0.1.16.dist-info/metadata.json
searchie_tools_yaml2json-0.1.16.dist-info/top_level.txt
yaml2json/__init__.py
yaml2json/version.py
