Metadata-Version: 2.0
Name: searchie-tools-yaml2json
Version: 0.1.16
Summary: Utility to convert YAML files to JSON format
Home-page: UNKNOWN
Author: Eugene Krokhalev
Author-email: rutsh@searchie.org
License: UNKNOWN
Platform: UNKNOWN
Classifier: Development Status :: 4 - Beta
Classifier: Environment :: Console
Classifier: Intended Audience :: Developers
Classifier: Intended Audience :: Information Technology
Classifier: Intended Audience :: System Administrators
Classifier: License :: OSI Approved :: MIT License
Classifier: Operating System :: POSIX
Classifier: Programming Language :: Python :: 2.7
Classifier: Programming Language :: Python :: 3
Classifier: Topic :: Software Development
Classifier: Topic :: Software Development :: Pre-processors
Classifier: Topic :: Utilities
Requires-Dist: pyyaml
